{"course":"geografia","videos":[{"slug":"geografia-clase-1-1-ceprevi-admision-unfv-lchpiu","title":"GEOGRAFÍA - CLASE 1.1 - CEPREVI - ADMISIÓN UNFV","videoId":"LcHpIuJdrDI","channel":"@TODOPRE","week":"1","questionKey":"geografia/semana-1","embedUrl":"https://www.youtube-nocookie.com/embed/LcHpIuJdrDI?rel=0&modestbranding=1"},{"slug":"geografia-clase-1-2-ceprevi-admision-unfv-kojkoi","title":"GEOGRAFÍA - CLASE 1.2 - CEPREVI - ADMISIÓN UNFV","videoId":"kOjKOIS1pQE","channel":"@TODOPRE","week":"1","questionKey":"geografia/semana-1","embedUrl":"https://www.youtube-nocookie.com/embed/kOjKOIS1pQE?rel=0&modestbranding=1"},{"slug":"geografia-clase-10-ceprevi-admision-unfv-g25cbw","title":"GEOGRAFÍA - CLASE 10 - CEPREVI - ADMISIÓN UNFV","videoId":"g25CbWHEtws","channel":"@TODOPRE","week":"10","questionKey":"geografia/semana-10","embedUrl":"https://www.youtube-nocookie.com/embed/g25CbWHEtws?rel=0&modestbranding=1"},{"slug":"geografia-clase-11-ceprevi-admision-unfv-yacfqk","title":"GEOGRAFÍA - CLASE 11 - CEPREVI - ADMISIÓN UNFV","videoId":"yAcFqK5FScw","channel":"@TODOPRE","week":"11","questionKey":"geografia/semana-11","embedUrl":"https://www.youtube-nocookie.com/embed/yAcFqK5FScw?rel=0&modestbranding=1"},{"slug":"geografia-clase-12-ceprevi-admision-unfv-imetb7","title":"GEOGRAFÍA - CLASE 12 - CEPREVI - ADMISIÓN UNFV","videoId":"iMeTB7huWAc","channel":"@TODOPRE","week":"12","questionKey":"geografia/semana-12","embedUrl":"https://www.youtube-nocookie.com/embed/iMeTB7huWAc?rel=0&modestbranding=1"},{"slug":"geografia-clase-13-ceprevi-admision-unfv-khqbk7","title":"GEOGRAFÍA - CLASE 13 - CEPREVI - ADMISIÓN UNFV","videoId":"KhqBk7b1kV4","channel":"@TODOPRE","week":"13","questionKey":"geografia/semana-13","embedUrl":"https://www.youtube-nocookie.com/embed/KhqBk7b1kV4?rel=0&modestbranding=1"},{"slug":"geografia-clase-14-ceprevi-admision-unfv-u8w7_v","title":"GEOGRAFÍA - CLASE 14 - CEPREVI - ADMISIÓN UNFV","videoId":"U8w7_VUrQrQ","channel":"@TODOPRE","week":"14","questionKey":"geografia/semana-14","embedUrl":"https://www.youtube-nocookie.com/embed/U8w7_VUrQrQ?rel=0&modestbranding=1"},{"slug":"geografia-clase-15-ceprevi-admision-unfv-dreeqn","title":"GEOGRAFÍA - CLASE 15 - CEPREVI - ADMISIÓN UNFV","videoId":"DrEeQNG1xrs","channel":"@TODOPRE","week":"15","questionKey":"geografia/semana-15","embedUrl":"https://www.youtube-nocookie.com/embed/DrEeQNG1xrs?rel=0&modestbranding=1"},{"slug":"geografia-clase-2-ceprevi-admision-unfv-alfrah","title":"GEOGRAFÍA - CLASE 2 - CEPREVI - ADMISIÓN UNFV","videoId":"alfrahAffWk","channel":"@TODOPRE","week":"2","questionKey":"geografia/semana-2","embedUrl":"https://www.youtube-nocookie.com/embed/alfrahAffWk?rel=0&modestbranding=1"},{"slug":"geografia-clase-3-ceprevi-admision-unfv-sykivd","title":"GEOGRAFÍA - CLASE 3 - CEPREVI - ADMISIÓN UNFV","videoId":"sYKivDFR7nI","channel":"@TODOPRE","week":"3","questionKey":"geografia/semana-3","embedUrl":"https://www.youtube-nocookie.com/embed/sYKivDFR7nI?rel=0&modestbranding=1"},{"slug":"geografia-clase-4-ceprevi-admision-unfv-zyyw4i","title":"GEOGRAFÍA - CLASE 4 - CEPREVI - ADMISIÓN UNFV","videoId":"ZYYW4iXWNT0","channel":"@TODOPRE","week":"4","questionKey":"geografia/semana-4","embedUrl":"https://www.youtube-nocookie.com/embed/ZYYW4iXWNT0?rel=0&modestbranding=1"},{"slug":"geografia-clase-5-ceprevi-admision-unfv-3zxlsx","title":"GEOGRAFÍA - CLASE 5 - CEPREVI - ADMISIÓN UNFV","videoId":"3zxlSxTlVpQ","channel":"@TODOPRE","week":"5","questionKey":"geografia/semana-5","embedUrl":"https://www.youtube-nocookie.com/embed/3zxlSxTlVpQ?rel=0&modestbranding=1"},{"slug":"geografia-clase-6-ceprevi-admision-unfv-azgqxd","title":"GEOGRAFÍA - CLASE 6 - CEPREVI - ADMISIÓN UNFV","videoId":"aZgqXDTeiMU","channel":"@TODOPRE","week":"6","questionKey":"geografia/semana-6","embedUrl":"https://www.youtube-nocookie.com/embed/aZgqXDTeiMU?rel=0&modestbranding=1"},{"slug":"geografia-clase-7-ceprevi-admision-unfv-drkyal","title":"GEOGRAFÍA - CLASE 7 - CEPREVI - ADMISIÓN UNFV","videoId":"dRKyAl5jJaw","channel":"@TODOPRE","week":"7","questionKey":"geografia/semana-7","embedUrl":"https://www.youtube-nocookie.com/embed/dRKyAl5jJaw?rel=0&modestbranding=1"},{"slug":"geografia-clase-8-ceprevi-admision-unfv-zsm6vp","title":"GEOGRAFÍA - CLASE 8 - CEPREVI - ADMISIÓN UNFV","videoId":"Zsm6vpSG7rs","channel":"@TODOPRE","week":"8","questionKey":"geografia/semana-8","embedUrl":"https://www.youtube-nocookie.com/embed/Zsm6vpSG7rs?rel=0&modestbranding=1"},{"slug":"geografia-clase-9-ceprevi-admision-unfv-b6skr_","title":"GEOGRAFÍA - CLASE 9 - CEPREVI - ADMISIÓN UNFV","videoId":"B6SKR_WEy1M","channel":"@TODOPRE","week":"9","questionKey":"geografia/semana-9","embedUrl":"https://www.youtube-nocookie.com/embed/B6SKR_WEy1M?rel=0&modestbranding=1"},{"slug":"geografia-y-educacion-civica-clase-1-pre-san-marcos-admision-unmsm-c4bfox","title":"GEOGRAFÍA Y EDUCACIÓN CÍVICA - Clase 1 - PRE SAN MARCOS - Admisión UNMSM","videoId":"c4bfoX-rpmc","channel":"@TODOPRE","week":"1","questionKey":"geografia/semana-1","embedUrl":"https://www.youtube-nocookie.com/embed/c4bfoX-rpmc?rel=0&modestbranding=1"},{"slug":"geografia-y-educacion-civica-clase-10-pre-san-marcos-admision-unmsm-onrnfw","title":"GEOGRAFÍA Y EDUCACIÓN CÍVICA - Clase 10 - PRE SAN MARCOS - Admisión UNMSM","videoId":"oNrNfWVREjU","channel":"@TODOPRE","week":"10","questionKey":"geografia/semana-10","embedUrl":"https://www.youtube-nocookie.com/embed/oNrNfWVREjU?rel=0&modestbranding=1"},{"slug":"geografia-y-educacion-civica-clase-10-1-pre-san-marcos-admision-unmsm-xp3byf","title":"GEOGRAFÍA Y EDUCACIÓN CÍVICA - Clase 10.1 - PRE SAN MARCOS - Admisión UNMSM","videoId":"xp3BYF_FZT4","channel":"@TODOPRE","week":"10","questionKey":"geografia/semana-10","embedUrl":"https://www.youtube-nocookie.com/embed/xp3BYF_FZT4?rel=0&modestbranding=1"},{"slug":"geografia-y-educacion-civica-clase-10-2-pre-san-marcos-admision-unmsm-fqz1p3","title":"GEOGRAFÍA Y EDUCACIÓN CÍVICA - Clase 10.2 - PRE SAN MARCOS - Admisión UNMSM","videoId":"FqZ1p3R3SZY","channel":"@TODOPRE","week":"10","questionKey":"geografia/semana-10","embedUrl":"https://www.youtube-nocookie.com/embed/FqZ1p3R3SZY?rel=0&modestbranding=1"},{"slug":"geografia-y-educacion-civica-clase-11-pre-san-marcos-admision-unmsm-gqs1sq","title":"GEOGRAFÍA Y EDUCACIÓN CÍVICA - Clase 11 - PRE SAN MARCOS - Admisión UNMSM","videoId":"gQS1sQnTuUE","channel":"@TODOPRE","week":"11","questionKey":"geografia/semana-11","embedUrl":"https://www.youtube-nocookie.com/embed/gQS1sQnTuUE?rel=0&modestbranding=1"},{"slug":"geografia-y-educacion-civica-clase-12-pre-san-marcos-admision-unmsm-by7xos","title":"GEOGRAFÍA Y EDUCACIÓN CÍVICA - Clase 12 - PRE SAN MARCOS - Admisión UNMSM","videoId":"BY7xoslj0ns","channel":"@TODOPRE","week":"12","questionKey":"geografia/semana-12","embedUrl":"https://www.youtube-nocookie.com/embed/BY7xoslj0ns?rel=0&modestbranding=1"},{"slug":"geografia-y-educacion-civica-clase-13-pre-san-marcos-admision-unmsm-s0p3ny","title":"GEOGRAFÍA Y EDUCACIÓN CÍVICA - Clase 13 - PRE SAN MARCOS - Admisión UNMSM","videoId":"s0P3Nyl9JWs","channel":"@TODOPRE","week":"13","questionKey":"geografia/semana-13","embedUrl":"https://www.youtube-nocookie.com/embed/s0P3Nyl9JWs?rel=0&modestbranding=1"},{"slug":"geografia-y-educacion-civica-clase-14-pre-san-marcos-admision-unmsm-bzxddg","title":"GEOGRAFÍA Y EDUCACIÓN CÍVICA - Clase 14 - PRE SAN MARCOS - Admisión UNMSM","videoId":"BzXDDgCFNXw","channel":"@TODOPRE","week":"14","questionKey":"geografia/semana-14","embedUrl":"https://www.youtube-nocookie.com/embed/BzXDDgCFNXw?rel=0&modestbranding=1"},{"slug":"geografia-y-educacion-civica-clase-15-pre-san-marcos-admision-unmsm-odmrcu","title":"GEOGRAFÍA Y EDUCACIÓN CÍVICA - Clase 15 - PRE SAN MARCOS - Admisión UNMSM","videoId":"oDMRCu7iosY","channel":"@TODOPRE","week":"15","questionKey":"geografia/semana-15","embedUrl":"https://www.youtube-nocookie.com/embed/oDMRCu7iosY?rel=0&modestbranding=1"},{"slug":"geografia-y-educacion-civica-clase-16-pre-san-marcos-admision-unmsm-c7odzd","title":"GEOGRAFÍA Y EDUCACIÓN CÍVICA - Clase 16 - PRE SAN MARCOS - Admisión UNMSM","videoId":"C7odZdrComE","channel":"@TODOPRE","week":"16","questionKey":"geografia/semana-16","embedUrl":"https://www.youtube-nocookie.com/embed/C7odZdrComE?rel=0&modestbranding=1"},{"slug":"geografia-y-educacion-civica-clase-17-pre-san-marcos-admision-unmsm-tp2_v2","title":"GEOGRAFÍA Y EDUCACIÓN CÍVICA - Clase 17 - PRE SAN MARCOS - Admisión UNMSM","videoId":"tp2_V24sfkc","channel":"@TODOPRE","week":"17","questionKey":"geografia/semana-17","embedUrl":"https://www.youtube-nocookie.com/embed/tp2_V24sfkc?rel=0&modestbranding=1"},{"slug":"geografia-y-educacion-civica-clase-18-pre-san-marcos-admision-unmsm-g0kwcc","title":"GEOGRAFÍA Y EDUCACIÓN CÍVICA - Clase 18 - PRE SAN MARCOS - Admisión UNMSM","videoId":"G0kwCCSDHGg","channel":"@TODOPRE","week":"18","questionKey":"geografia/semana-18","embedUrl":"https://www.youtube-nocookie.com/embed/G0kwCCSDHGg?rel=0&modestbranding=1"},{"slug":"geografia-y-educacion-civica-clase-2-pre-san-marcos-admision-unmsm-qiye2k","title":"GEOGRAFÍA Y EDUCACIÓN CÍVICA - Clase 2 - PRE SAN MARCOS - Admisión UNMSM","videoId":"Qiye2KtTAHQ","channel":"@TODOPRE","week":"2","questionKey":"geografia/semana-2","embedUrl":"https://www.youtube-nocookie.com/embed/Qiye2KtTAHQ?rel=0&modestbranding=1"},{"slug":"geografia-y-educacion-civica-clase-3-pre-san-marcos-admision-unmsm-3-5bhh","title":"GEOGRAFÍA Y EDUCACIÓN CÍVICA - Clase 3 - PRE SAN MARCOS - Admisión UNMSM","videoId":"3-5BHHOsyYA","channel":"@TODOPRE","week":"3","questionKey":"geografia/semana-3","embedUrl":"https://www.youtube-nocookie.com/embed/3-5BHHOsyYA?rel=0&modestbranding=1"},{"slug":"geografia-y-educacion-civica-clase-4-pre-san-marcos-admision-unmsm-iarwit","title":"GEOGRAFÍA Y EDUCACIÓN CÍVICA - Clase 4 - PRE SAN MARCOS - Admisión UNMSM","videoId":"IARWIthH0rU","channel":"@TODOPRE","week":"4","questionKey":"geografia/semana-4","embedUrl":"https://www.youtube-nocookie.com/embed/IARWIthH0rU?rel=0&modestbranding=1"},{"slug":"geografia-y-educacion-civica-clase-5-pre-san-marcos-admision-unmsm-ocgver","title":"GEOGRAFÍA Y EDUCACIÓN CÍVICA - Clase 5 - PRE SAN MARCOS - Admisión UNMSM","videoId":"ocGverNDM6c","channel":"@TODOPRE","week":"5","questionKey":"geografia/semana-5","embedUrl":"https://www.youtube-nocookie.com/embed/ocGverNDM6c?rel=0&modestbranding=1"},{"slug":"geografia-y-educacion-civica-clase-6-pre-san-marcos-admision-unmsm-wi6zzl","title":"GEOGRAFÍA Y EDUCACIÓN CÍVICA - Clase 6 - PRE SAN MARCOS - Admisión UNMSM","videoId":"wi6ZZloH3B0","channel":"@TODOPRE","week":"6","questionKey":"geografia/semana-6","embedUrl":"https://www.youtube-nocookie.com/embed/wi6ZZloH3B0?rel=0&modestbranding=1"},{"slug":"geografia-y-educacion-civica-clase-7-pre-san-marcos-admision-unmsm-xx-9z6","title":"GEOGRAFÍA Y EDUCACIÓN CÍVICA - Clase 7 - PRE SAN MARCOS - Admisión UNMSM","videoId":"XX-9Z6Gz3mM","channel":"@TODOPRE","week":"7","questionKey":"geografia/semana-7","embedUrl":"https://www.youtube-nocookie.com/embed/XX-9Z6Gz3mM?rel=0&modestbranding=1"},{"slug":"geografia-y-educacion-civica-clase-8-pre-san-marcos-admision-unmsm-1amas_","title":"GEOGRAFÍA Y EDUCACIÓN CÍVICA - Clase 8 - PRE SAN MARCOS - Admisión UNMSM","videoId":"1aMaS_VfNDc","channel":"@TODOPRE","week":"8","questionKey":"geografia/semana-8","embedUrl":"https://www.youtube-nocookie.com/embed/1aMaS_VfNDc?rel=0&modestbranding=1"},{"slug":"geografia-y-educacion-civica-clase-9-pre-san-marcos-admision-unmsm-bpt9hg","title":"GEOGRAFÍA Y EDUCACIÓN CÍVICA - Clase 9 - PRE SAN MARCOS - Admisión UNMSM","videoId":"BPt9HGH2bbI","channel":"@TODOPRE","week":"9","questionKey":"geografia/semana-9","embedUrl":"https://www.youtube-nocookie.com/embed/BPt9HGH2bbI?rel=0&modestbranding=1"},{"slug":"geografia-y-educacion-civica-repaso-temario-completo-general-pre-san-mar-abr4qr","title":"GEOGRAFÍA Y EDUCACIÓN CÍVICA - Repaso Temario Completo (General) - PRE SAN MARCOS - Admisión UNMSM","videoId":"abr4QRoP-DU","channel":"@TODOPRE","week":"","questionKey":"geografia/general","embedUrl":"https://www.youtube-nocookie.com/embed/abr4QRoP-DU?rel=0&modestbranding=1"},{"slug":"geografia-semana-1-teoria-geografica-y-la-localizacion-ue9ins","title":"GEOGRAFÍA | Semana 1: Teoría geográfica y la localización","videoId":"uE9inSxqjhY","channel":"@universepre_official","week":"1","questionKey":"geografia/semana-1","embedUrl":"https://www.youtube-nocookie.com/embed/uE9inSxqjhY?rel=0&modestbranding=1"},{"slug":"geografia-semana-2-representacion-del-espacio-geografico-66eyc0","title":"GEOGRAFÍA | Semana 2: Representación del espacio geográfico","videoId":"66eYc05mfeU","channel":"@universepre_official","week":"2","questionKey":"geografia/semana-2","embedUrl":"https://www.youtube-nocookie.com/embed/66eYc05mfeU?rel=0&modestbranding=1"},{"slug":"geografia-semana-3-peru-en-un-contexto-geopolitico-zvlaox","title":"GEOGRAFÍA | Semana 3: Perú en un contexto geopolítico","videoId":"zvlaoxbbDrc","channel":"@universepre_official","week":"3","questionKey":"geografia/semana-3","embedUrl":"https://www.youtube-nocookie.com/embed/zvlaoxbbDrc?rel=0&modestbranding=1"},{"slug":"geografia-semana-4-peru-y-los-acuerdos-de-integracion-if0vz9","title":"GEOGRAFÍA | Semana 4: Perú y los acuerdos de integración","videoId":"if0vZ9jOMB8","channel":"@universepre_official","week":"4","questionKey":"geografia/semana-4","embedUrl":"https://www.youtube-nocookie.com/embed/if0vZ9jOMB8?rel=0&modestbranding=1"},{"slug":"geografia-semana-5-geografia-humana-dinamica-poblacional-ykn32a","title":"GEOGRAFÍA | Semana 5: Geografía humana - Dinámica poblacional","videoId":"yKn32AiGxEQ","channel":"@universepre_official","week":"5","questionKey":"geografia/semana-5","embedUrl":"https://www.youtube-nocookie.com/embed/yKn32AiGxEQ?rel=0&modestbranding=1"},{"slug":"geografia-semana-6-estado-peruano-vrjxna","title":"GEOGRAFÍA | Semana 6: Estado Peruano","videoId":"vrJxnA62BUo","channel":"@universepre_official","week":"6","questionKey":"geografia/semana-6","embedUrl":"https://www.youtube-nocookie.com/embed/vrJxnA62BUo?rel=0&modestbranding=1"},{"slug":"geografia-superresumen-para-2da-pc-cepreuni-kgks1z","title":"GEOGRAFÍA | SUPERRESUMEN para 2da PC CEPREUNI","videoId":"KGkS1ZDK5-Y","channel":"@universepre_official","week":"","questionKey":"","embedUrl":"https://www.youtube-nocookie.com/embed/KGkS1ZDK5-Y?rel=0&modestbranding=1"}]}